odoo/addons/stock_weighing_auto_create_lot/README.rst
odoo/addons/stock_weighing_auto_create_lot/__init__.py
odoo/addons/stock_weighing_auto_create_lot/__manifest__.py
odoo/addons/stock_weighing_auto_create_lot/i18n/es.po
odoo/addons/stock_weighing_auto_create_lot/i18n/nl.po
odoo/addons/stock_weighing_auto_create_lot/i18n/stock_weighing_auto_create_lot.pot
odoo/addons/stock_weighing_auto_create_lot/readme/CONFIGURE.md
odoo/addons/stock_weighing_auto_create_lot/readme/CONTRIBUTORS.md
odoo/addons/stock_weighing_auto_create_lot/readme/DESCRIPTION.md
odoo/addons/stock_weighing_auto_create_lot/static/description/icon.png
odoo/addons/stock_weighing_auto_create_lot/static/description/index.html
odoo/addons/stock_weighing_auto_create_lot/wizards/__init__.py
odoo/addons/stock_weighing_auto_create_lot/wizards/weighing_wizard.py
odoo/addons/stock_weighing_auto_create_lot/wizards/weighing_wizard_views.xml
odoo_addon_stock_weighing_auto_create_lot-15.0.1.0.0.5.dist-info/METADATA
odoo_addon_stock_weighing_auto_create_lot-15.0.1.0.0.5.dist-info/WHEEL
odoo_addon_stock_weighing_auto_create_lot-15.0.1.0.0.5.dist-info/top_level.txt
odoo_addon_stock_weighing_auto_create_lot-15.0.1.0.0.5.dist-info/RECORD
